[
  {
    "start_pose": {
      "pan": 305,
      "tilt": 18,
      "zoom": 50,
      "wait_time_ms": 3000
    },
    "end_pose": {
      "pan": 90,
      "tilt": -3,
      "zoom": 50,
      "wait_time_ms": 3000
    },
    "nr_steps": 30
  },
  {
    "start_pose": {
      "pan": 305,
      "tilt": 30,
      "zoom": 147,
      "wait_time_ms": 3000
    },
    "end_pose": {
      "pan": 200,
      "tilt": -10,
      "zoom": 147,
      "wait_time_ms": 3000
    },
    "nr_steps": 20
  },
  {
    "start_pose": {
      "pan": 200,
      "tilt": -10,
      "zoom": 147,
      "wait_time_ms": 3000
    },
    "end_pose": {
      "pan": 90,
      "tilt": 0,
      "zoom": 147,
      "wait_time_ms": 3000
    },
    "nr_steps": 20
  },
  {
    "start_pose": {
      "pan": 305,
      "tilt": 15,
      "zoom": 147,
      "wait_time_ms": 3000
    },
    "end_pose": {
      "pan": 200,
      "tilt": -23,
      "zoom": 147,
      "wait_time_ms": 3000
    },
    "nr_steps": 20
  },
  {
    "start_pose": {
      "pan": 200,
      "tilt": -23,
      "zoom": 147,
      "wait_time_ms": 3000
    },
    "end_pose": {
      "pan": 90,
      "tilt": -13,
      "zoom": 147,
      "wait_time_ms": 3000
    },
    "nr_steps": 20
  }
]